{
  "id": "b8e0fe42-2a34-45c8-9887-pos-backend-env",
  "name": "POS Backend Local",
  "values": [
    {
      "key": "base_url",
      "value": "http://127.0.0.1:8000/api",
      "type": "default",
      "enabled": true
    },
    {
      "key": "username",
      "value": "ALFRED",
      "type": "default",
      "enabled": true
    },
    {
      "key": "password",
      "value": "",
      "type": "secret",
      "enabled": true
    },
    {
      "key": "access_token",
      "value": "",
      "type": "secret",
      "enabled": true
    },
    {
      "key": "refresh_token",
      "value": "",
      "type": "secret",
      "enabled": true
    },
    {
      "key": "product_id",
      "value": "1",
      "type": "default",
      "enabled": true
    },
    {
      "key": "sale_id",
      "value": "1",
      "type": "default",
      "enabled": true
    }
  ],
  "_postman_variable_scope": "environment",
  "_postman_exported_using": "Codex"
}
